README.md
setup.cfg
setup.py
doc/__init__.py
doc/conf.py
gentex/__init__.py
gentex/comat.py
gentex/features.py
gentex/makecomat.c
gentex/sphere.py
gentex/template.py
gentex/texmeas.py
gentex.egg-info/PKG-INFO
gentex.egg-info/SOURCES.txt
gentex.egg-info/dependency_links.txt
gentex.egg-info/requires.txt
gentex.egg-info/top_level.txt
tests/__init__.py
tests/test_comat.py
tests/test_sphere.py
tests/test_template.py
tests/test_texture_measure.py