Metadata-Version: 2.1
Name: gentex
Version: 0.1.2
Summary: General Texture Analysis
Home-page: https://github.com/NPann/GenTex
Author: GenTex contributors
License: UNKNOWN
Platform: UNKNOWN
Classifier: Programming Language :: Python :: 3
Classifier: Programming Language :: Python :: 3 :: Only
Classifier: License :: OSI Approved :: BSD License
Classifier: Operating System :: OS Independent
Classifier: Development Status :: 4 - Beta
Classifier: Topic :: Scientific/Engineering :: Information Analysis
Requires-Python: >=3.7
